{"version": 0.6, "generator": "Overpass API 0.7.62.1 084b4234", "osm3s": {"timestamp_osm_base": "2024-04-26T21:28:28Z", "copyright": "The data included in this document is from www.openstreetmap.org. The data is made available under ODbL."}, "elements": [{"type": "node", "id": 286841222, "lat": 41.9757477, "lon": -87.779528}, {"type": "node", "id": 286841223, "lat": 41.9774007, "lon": -87.7795168}, {"type": "node", "id": 286841225, "lat": 41.9773958, "lon": -87.7782229}, {"type": "node", "id": 286841226, "lat": 41.9757292, "lon": -87.778288}, {"type": "node", "id": 305904970, "lat": 41.9723961, "lon": -87.7601075}, {"type": "node", "id": 305904971, "lat": 41.9716079, "lon": -87.7600776}, {"type": "node", "id": 305904972, "lat": 41.9716073, "lon": -87.7577324}, {"type": "node", "id": 305904973, "lat": 41.9724227, "lon": -87.7577275}, {"type": "node", "id": 305905014, "lat": 41.9724366, "lon": -87.7553153}, {"type": "node", "id": 305905015, "lat": 41.9720709, "lon": -87.7553062}, {"type": "node", "id": 305905016, "lat": 41.9720624, "lon": -87.7559214}, {"type": "node", "id": 305905017, "lat": 41.9716896, "lon": -87.7559121}, {"type": "node", "id": 305905018, "lat": 41.9716672, "lon": -87.757542}, {"type": "node", "id": 305905019, "lat": 41.9724056, "lon": -87.7575604}, {"type": "node", "id": 305905635, "lat": 41.9810466, "lon": -87.7670296}, {"type": "node", "id": 305905636, "lat": 41.9810404, "lon": -87.7660602}, {"type": "node", "id": 305905637, "lat": 41.9794062, "lon": -87.766079}, {"type": "node", "id": 305905638, "lat": 41.9794124, "lon": -87.7670484}, {"type": "node", "id": 305906790, "lat": 41.9677478, "lon": -87.7626843}, {"type": "node", "id": 305906791, "lat": 41.9681404, "lon": -87.7626586}, {"type": "node", "id": 305906792, "lat": 41.9688041, "lon": -87.7623496}, {"type": "node", "id": 305906793, "lat": 41.9695131, "lon": -87.7649828}, {"type": "node", "id": 305906794, "lat": 41.9678672, "lon": -87.7649126}, {"type": "node", "id": 354106589, "lat": 41.9784216, "lon": -87.7731655}, {"type": "node", "id": 354214183, "lat": 41.9695939, "lon": -87.7753723}, {"type": "node", "id": 757950925, "lat": 41.9772518, "lon": -87.7697838, "tags": {"addr:city": "Chicago", "addr:housenumber": "5316", "addr:postcode": "60630", "addr:state": "IL", "addr:street": "North Milwaukee Avenue", "addr:unit": "M", "brand": "7-Eleven", "brand:wikidata": "Q259340", "name": "7-Eleven", "shop": "convenience", "website": "https://www.7-eleven.com/locations/il/chicago/5316-m-n-milwaukee-avenue-33067"}}, {"type": "node", "id": 1745518192, "lat": 41.9679588, "lon": -87.7606604}, {"type": "node", "id": 1745518238, "lat": 41.9679805, "lon": -87.7606161}, {"type": "node", "id": 1745518263, "lat": 41.9680095, "lon": -87.7607055}, {"type": "node", "id": 1745518390, "lat": 41.9680661, "lon": -87.7604443}, {"type": "node", "id": 1745518690, "lat": 41.9681171, "lon": -87.7604917}, {"type": "node", "id": 1745526356, "lat": 41.9694732, "lon": -87.7627962}, {"type": "node", "id": 1745526416, "lat": 41.9694787, "lon": -87.7627851}, {"type": "node", "id": 1745526774, "lat": 41.9694964, "lon": -87.7627592}, {"type": "node", "id": 1745526891, "lat": 41.9695119, "lon": -87.7628547}, {"type": "node", "id": 1745527030, "lat": 41.9695344, "lon": -87.7626816}, {"type": "node", "id": 1745527281, "lat": 41.969556, "lon": -87.7626171}, {"type": "node", "id": 1745527366, "lat": 41.9695716, "lon": -87.7627107}, {"type": "node", "id": 1745527428, "lat": 41.9695785, "lon": -87.762718}, {"type": "node", "id": 1745527899, "lat": 41.9696335, "lon": -87.762462}, {"type": "node", "id": 1745528296, "lat": 41.9696776, "lon": -87.762502}, {"type": "node", "id": 1746214377, "lat": 41.973994, "lon": -87.7657824}, {"type": "node", "id": 1746214513, "lat": 41.9740211, "lon": -87.7659881}, {"type": "node", "id": 1746214695, "lat": 41.9740647, "lon": -87.7656512}, {"type": "node", "id": 1746214750, "lat": 41.9740822, "lon": -87.7658607}, {"type": "node", "id": 1746214924, "lat": 41.9741516, "lon": -87.7657295}, {"type": "node", "id": 1746214955, "lat": 41.9741638, "lon": -87.765711}, {"type": "node", "id": 1746215787, "lat": 41.9745861, "lon": -87.7664832}, {"type": "node", "id": 1746216238, "lat": 41.9747179, "lon": -87.7662173}, {"type": "node", "id": 1749353274, "lat": 41.9686262, "lon": -87.7784568}, {"type": "node", "id": 1749353275, "lat": 41.9686265, "lon": -87.7785138}, {"type": "node", "id": 1749353285, "lat": 41.968645, "lon": -87.7786497}, {"type": "node", "id": 1749353287, "lat": 41.9686457, "lon": -87.7785154}, {"type": "node", "id": 1749353623, "lat": 41.9687568, "lon": -87.7781548}, {"type": "node", "id": 1749353634, "lat": 41.9687597, "lon": -87.7778974}, {"type": "node", "id": 1749353804, "lat": 41.9688316, "lon": -87.7786517}, {"type": "node", "id": 1749353813, "lat": 41.9688356, "lon": -87.778637}, {"type": "node", "id": 1749353818, "lat": 41.9688375, "lon": -87.7784605}, {"type": "node", "id": 1749353843, "lat": 41.9688433, "lon": -87.7781559}, {"type": "node", "id": 1749353851, "lat": 41.9688462, "lon": -87.7779003}, {"type": "node", "id": 1749363459, "lat": 41.9714741, "lon": -87.7714826}, {"type": "node", "id": 1749363541, "lat": 41.9714992, "lon": -87.771578}, {"type": "node", "id": 1749364287, "lat": 41.9716972, "lon": -87.7713758}, {"type": "node", "id": 1749364352, "lat": 41.9717224, "lon": -87.7714712}, {"type": "node", "id": 1749366851, "lat": 41.9725644, "lon": -87.7756119}, {"type": "node", "id": 1749366891, "lat": 41.9725868, "lon": -87.7756945}, {"type": "node", "id": 1749366893, "lat": 41.9725933, "lon": -87.7777533}, {"type": "node", "id": 1749367098, "lat": 41.9726482, "lon": -87.7779562}, {"type": "node", "id": 1749367176, "lat": 41.9726752, "lon": -87.777943}, {"type": "node", "id": 1749367225, "lat": 41.9726992, "lon": -87.7778706}, {"type": "node", "id": 1749367306, "lat": 41.9727228, "lon": -87.7778847}, {"type": "node", "id": 1749367312, "lat": 41.9727256, "lon": -87.7778043}, {"type": "node", "id": 1749367393, "lat": 41.9727367, "lon": -87.7776832}, {"type": "node", "id": 1749367414, "lat": 41.9727441, "lon": -87.7778203}, {"type": "node", "id": 1749367426, "lat": 41.9727502, "lon": -87.7777331}, {"type": "node", "id": 1749367645, "lat": 41.9728122, "lon": -87.7754939}, {"type": "node", "id": 1749367685, "lat": 41.9728206, "lon": -87.775527}, {"type": "node", "id": 1749367796, "lat": 41.9728658, "lon": -87.7755063}, {"type": "node", "id": 1749367857, "lat": 41.9728798, "lon": -87.7755614}, {"type": "node", "id": 1749367938, "lat": 41.9729021, "lon": -87.7756384}, {"type": "node", "id": 1749367996, "lat": 41.9729226, "lon": -87.7756272}, {"type": "node", "id": 1749368051, "lat": 41.972938, "lon": -87.7756896}, {"type": "node", "id": 1749370372, "lat": 41.9736053, "lon": -87.7785084}, {"type": "node", "id": 1749370395, "lat": 41.9736092, "lon": -87.7784679}, {"type": "node", "id": 1749370435, "lat": 41.9736134, "lon": -87.7784826}, {"type": "node", "id": 1749370620, "lat": 41.9736429, "lon": -87.7786276}, {"type": "node", "id": 1749370754, "lat": 41.9736636, "lon": -87.7786366}, {"type": "node", "id": 1749370787, "lat": 41.9736692, "lon": -87.7786549}, {"type": "node", "id": 1749371059, "lat": 41.9737143, "lon": -87.7786288}, {"type": "node", "id": 1749371105, "lat": 41.9737254, "lon": -87.7786618}, {"type": "node", "id": 1749371111, "lat": 41.9737269, "lon": -87.7783988}, {"type": "node", "id": 1749371286, "lat": 41.9737718, "lon": -87.7785933}, {"type": "node", "id": 1749371325, "lat": 41.9737815, "lon": -87.7786282}, {"type": "node", "id": 1749371333, "lat": 41.9737868, "lon": -87.7785859}, {"type": "node", "id": 1749664210, "lat": 41.9759538, "lon": -87.770875}, {"type": "node", "id": 1749665651, "lat": 41.9762678, "lon": -87.7705597}, {"type": "node", "id": 1749665672, "lat": 41.9762832, "lon": -87.7714661}, {"type": "node", "id": 1749665929, "lat": 41.976337, "lon": -87.7868416}, {"type": "node", "id": 1749666090, "lat": 41.976401, "lon": -87.7870341}, {"type": "node", "id": 1749666254, "lat": 41.9764533, "lon": -87.7867725}, {"type": "node", "id": 1749666420, "lat": 41.9764995, "lon": -87.7691234}, {"type": "node", "id": 1749666433, "lat": 41.9765173, "lon": -87.7869651}, {"type": "node", "id": 1749666612, "lat": 41.9765973, "lon": -87.7711507}, {"type": "node", "id": 1749666667, "lat": 41.9766354, "lon": -87.7688574}, {"type": "node", "id": 1749666768, "lat": 41.976669, "lon": -87.7692782}, {"type": "node", "id": 1749667082, "lat": 41.9768049, "lon": -87.7690122}, {"type": "node", "id": 1749669291, "lat": 41.9776297, "lon": -87.7701505}, {"type": "node", "id": 1749669564, "lat": 41.9776834, "lon": -87.7701978}, {"type": "node", "id": 1749669797, "lat": 41.9777615, "lon": -87.7698919}, {"type": "node", "id": 1749669859, "lat": 41.977789, "lon": -87.7699156}, {"type": "node", "id": 1749669861, "lat": 41.9777894, "lon": -87.7699891}, {"type": "node", "id": 1749670020, "lat": 41.9778139, "lon": -87.7699392}, {"type": "node", "id": 2053512391, "lat": 41.9798791, "lon": -87.7731739}, {"type": "node", "id": 2053512397, "lat": 41.9788941, "lon": -87.7722458}, {"type": "node", "id": 2053512399, "lat": 41.9784295, "lon": -87.7731953}, {"type": "node", "id": 2053512409, "lat": 41.978916, "lon": -87.7722458}, {"type": "node", "id": 2053512411, "lat": 41.9798591, "lon": -87.7731846}, {"type": "node", "id": 2053512415, "lat": 41.9798771, "lon": -87.7731229}, {"type": "node", "id": 2053512420, "lat": 41.9788755, "lon": -87.7722575}, {"type": "node", "id": 2053512464, "lat": 41.9789439, "lon": -87.7722646}, {"type": "node", "id": 2053512466, "lat": 41.979885, "lon": -87.773147}, {"type": "node", "id": 2053512468, "lat": 41.9784674, "lon": -87.7732114}, {"type": "node", "id": 2053512491, "lat": 41.9784454, "lon": -87.773206}, {"type": "node", "id": 2053834244, "lat": 41.9759962, "lon": -87.7634049}, {"type": "node", "id": 2053834260, "lat": 41.9761656, "lon": -87.7642145}, {"type": "node", "id": 2053834261, "lat": 41.976, "lon": -87.7631769}, {"type": "node", "id": 2053834266, "lat": 41.9758058, "lon": -87.7634025}, {"type": "node", "id": 2053834272, "lat": 41.9758197, "lon": -87.7640814}, {"type": "node", "id": 2053834273, "lat": 41.976546, "lon": -87.7637027}, {"type": "node", "id": 2078125275, "lat": 41.9973375, "lon": -87.7801456}, {"type": "node", "id": 2078125643, "lat": 41.9971211, "lon": -87.7801174}, {"type": "node", "id": 2078187694, "lat": 41.9903028, "lon": -87.7662377}, {"type": "node", "id": 2144878273, "lat": 41.971621, "lon": -87.7577036}, {"type": "node", "id": 2144878296, "lat": 41.9678949, "lon": -87.7649549}, {"type": "node", "id": 2144878359, "lat": 41.9724274, "lon": -87.7600764}, {"type": "node", "id": 2144878373, "lat": 41.9678751, "lon": -87.7649394}, {"type": "node", "id": 2144878387, "lat": 41.9724464, "lon": -87.757748}, {"type": "node", "id": 2144878408, "lat": 41.967917, "lon": -87.7649615}, {"type": "node", "id": 2144878413, "lat": 41.9724293, "lon": -87.7600421}, {"type": "node", "id": 2144878420, "lat": 41.9716098, "lon": -87.7577147}, {"type": "node", "id": 2144878422, "lat": 41.9715938, "lon": -87.760067}, {"type": "node", "id": 2144878427, "lat": 41.9715839, "lon": -87.7600323}, {"type": "node", "id": 2144878441, "lat": 41.9724516, "lon": -87.757768}, {"type": "node", "id": 2144878499, "lat": 41.9724367, "lon": -87.7577333}, {"type": "node", "id": 2144878523, "lat": 41.9716355, "lon": -87.7577}, {"type": "node", "id": 2144878534, "lat": 41.9715867, "lon": -87.7600554}, {"type": "node", "id": 2144878563, "lat": 41.9724135, "lon": -87.7601011}, {"type": "node", "id": 2144916905, "lat": 41.969546, "lon": -87.7649131}, {"type": "node", "id": 2144916942, "lat": 41.9695507, "lon": -87.7649409}, {"type": "node", "id": 2144916946, "lat": 41.9695467, "lon": -87.7649628}, {"type": "node", "id": 2144916964, "lat": 41.9695323, "lon": -87.7649773}, {"type": "node", "id": 2144919888, "lat": 41.9699243, "lon": -87.7746536}, {"type": "node", "id": 2144919891, "lat": 41.9699273, "lon": -87.7743759}, {"type": "node", "id": 2144919914, "lat": 41.9696019, "lon": -87.7746473}, {"type": "node", "id": 2144919918, "lat": 41.9702008, "lon": -87.7743812}, {"type": "node", "id": 2168616067, "lat": 41.9774146, "lon": -87.7782262}, {"type": "node", "id": 2168616069, "lat": 41.9757269, "lon": -87.7783107}, {"type": "node", "id": 2168616072, "lat": 41.9757247, "lon": -87.7794794}, {"type": "node", "id": 2168616075, "lat": 41.9757445, "lon": -87.7782727}, {"type": "node", "id": 2168616082, "lat": 41.9757719, "lon": -87.7795353}, {"type": "node", "id": 2168616093, "lat": 41.9774408, "lon": -87.7794626}, {"type": "node", "id": 2168616095, "lat": 41.9774182, "lon": -87.7795066}, {"type": "node", "id": 2168616099, "lat": 41.9774305, "lon": -87.7782435}, {"type": "node", "id": 2168616115, "lat": 41.9774398, "lon": -87.7782733}, {"type": "node", "id": 2168616125, "lat": 41.9757626, "lon": -87.7782727}, {"type": "node", "id": 2168616159, "lat": 41.9774344, "lon": -87.7794839}, {"type": "node", "id": 2168616169, "lat": 41.9757293, "lon": -87.7795105}, {"type": "node", "id": 2169870976, "lat": 41.9701901, "lon": -87.7753841}, {"type": "node", "id": 2838650361, "lat": 41.9840534, "lon": -87.7604736}, {"type": "node", "id": 2838650362, "lat": 41.9840544, "lon": -87.7601974}, {"type": "node", "id": 2838650363, "lat": 41.984834, "lon": -87.7602054}, {"type": "node", "id": 2838650364, "lat": 41.984834, "lon": -87.7604843}, {"type": "node", "id": 3358447985, "lat": 41.9801177, "lon": -87.7572308}, {"type": "node", "id": 3358447986, "lat": 41.9793091, "lon": -87.7581271}, {"type": "node", "id": 3358447987, "lat": 41.9789724, "lon": -87.7575774}, {"type": "node", "id": 3358447988, "lat": 41.9797273, "lon": -87.7568435}, {"type": "node", "id": 3358447989, "lat": 41.9798017, "lon": -87.7569649}, {"type": "node", "id": 3358447990, "lat": 41.9798929, "lon": -87.7568638}, {"type": "node", "id": 4142069187, "lat": 41.9686027, "lon": -87.7817888, "tags": {"addr:city": "Chicago", "addr:housenumber": "6124", "addr:postcode": "60630", "addr:state": "IL", "addr:street": "West Gunnison Street", "amenity": "bar", "name": "Friendly Tavern", "phone": "+1-773-763-9796"}}, {"type": "node", "id": 4170809723, "lat": 41.969341, "lon": -87.7610394, "tags": {"addr:city": "Chicago", "addr:housenumber": "4859", "addr:postcode": "60630", "addr:state": "IL", "addr:street": "North Milwaukee Avenue", "brand": "7-Eleven", "brand:wikidata": "Q259340", "contact:website": "https://www.7-eleven.com/locations/il/chicago/4859-n-milwaukee-ave-33591", "name": "7-Eleven", "shop": "convenience"}}, {"type": "node", "id": 4172392092, "lat": 41.9691016, "lon": -87.7621393, "tags": {"amenity": "atm", "drive_through": "yes"}}, {"type": "node", "id": 4172392093, "lat": 41.97003, "lon": -87.7628353}, {"type": "node", "id": 4172392094, "lat": 41.9698623, "lon": -87.7631699}, {"type": "node", "id": 4172392095, "lat": 41.9697858, "lon": -87.7631007}, {"type": "node", "id": 4172392096, "lat": 41.9697432, "lon": -87.7631857}, {"type": "node", "id": 4172392097, "lat": 41.9697022, "lon": -87.7631474}, {"type": "node", "id": 4172392098, "lat": 41.9699171, "lon": -87.7627296}, {"type": "node", "id": 4172392099, "lat": 41.9707527, "lon": -87.7631387, "tags": {"addr:city": "Chicago", "addr:housenumber": "4943", "addr:postcode": "60630", "addr:state": "IL", "addr:street": "North Milwaukee Avenue", "name": "ANG Convenience Store", "shop": "convenience"}}, {"type": "node", "id": 4172392103, "lat": 41.9708434, "lon": -87.7632141, "tags": {"addr:city": "Chicago", "addr:housenumber": "4945", "addr:postcode": "60630", "addr:state": "IL", "addr:street": "North Milwaukee Avenue", "amenity": "restaurant", "cuisine": "sushi", "delivery": "yes", "name": "Gorilla Sushi Bar", "takeaway": "yes"}}, {"type": "node", "id": 4186479468, "lat": 41.9705905, "lon": -87.7626602, "tags": {"addr:city": "Chicago", "addr:housenumber": "5364", "addr:postcode": "60630", "addr:state": "IL", "addr:street": "West Gale Street", "amenity": "restaurant", "cuisine": "american", "delivery": "no", "name": "Jefferson Park Grill"}}, {"type": "node", "id": 4186479470, "lat": 41.9679485, "lon": -87.7610248, "tags": {"addr:city": "Chicago", "addr:housenumber": "4802", "addr:postcode": "60630", "addr:state": "IL", "addr:street": "North Milwaukee Avenue", "amenity": "theatre", "name": "The Gift Theatre"}}, {"type": "node", "id": 4186479471, "lat": 41.9680695, "lon": -87.7610792}, {"type": "node", "id": 4186479475, "lat": 41.9681174, "lon": -87.761121}, {"type": "node", "id": 4186479476, "lat": 41.9679337, "lon": -87.7613616}, {"type": "node", "id": 4186479477, "lat": 41.9679822, "lon": -87.7614041}, {"type": "node", "id": 4186624668, "lat": 41.9687569, "lon": -87.7781439}, {"type": "node", "id": 4186624671, "lat": 41.9687595, "lon": -87.7779182}, {"type": "node", "id": 4186821640, "lat": 41.969289, "lon": -87.7609822, "tags": {"addr:city": "Chicago", "addr:housenumber": "4859", "addr:postcode": "60630", "addr:state": "IL", "addr:street": "North Milwaukee Avenue", "amenity": "restaurant", "cuisine": "filipino", "name": "Kawayan"}}, {"type": "node", "id": 4238856142, "lat": 41.9721881, "lon": -87.7740893, "tags": {"addr:city": "Chicago", "addr:housenumber": "5814", "addr:postcode": "60630", "addr:state": "IL", "addr:street": "West Higgins Avenue", "name": "Beautiful Cakes", "phone": "+1-773-777-7535", "shop": "bakery", "website": "https://www.beautifulcakeschicago.com/"}}, {"type": "node", "id": 4251112646, "lat": 41.9763742, "lon": -87.7876462, "tags": {"amenity": "atm", "brand": "PNC Bank", "brand:wikidata": "Q38928", "cash_in": "yes", "drive_through": "no", "operator": "PNC Bank", "operator:wikidata": "Q38928"}}, {"type": "node", "id": 4251112647, "lat": 41.9766351, "lon": -87.7876377, "tags": {"amenity": "atm", "brand": "PNC Bank", "brand:wikidata": "Q38928", "cash_in": "yes", "currency:USD": "yes", "drive_through": "yes", "name": "PNC Bank", "operator": "PNC Bank", "operator:wikidata": "Q38928", "operator:wikipedia": "en:PNC Financial Services"}}, {"type": "node", "id": 4261931487, "lat": 41.976069, "lon": -87.7676499, "tags": {"addr:city": "Chicago", "addr:housenumber": "5255", "addr:postcode": "60630", "addr:state": "IL", "addr:street": "North Milwaukee Avenue", "amenity": "restaurant", "brand": "Jet's Pizza", "brand:wikidata": "Q16997713", "cuisine": "pizza", "name": "Jet's Pizza", "website": "https://www.jetspizza.com/stores/illinois/chicago/5255-n-milwaukee-ave/"}}, {"type": "node", "id": 4263626450, "lat": 41.9771698, "lon": -87.7697283, "tags": {"addr:city": "Chicago", "addr:housenumber": "5316", "addr:postcode": "60630", "addr:state": "IL", "addr:street": "North Milwaukee Avenue", "amenity": "restaurant", "cuisine": "chinese", "name": "Chinese Kitchen"}}, {"type": "node", "id": 4263932170, "lat": 41.9775973, "lon": -87.7691061, "tags": {"addr:city": "Chicago", "addr:housenumber": "5333", "addr:postcode": "60630", "addr:state": "IL", "addr:street": "North Milwaukee Avenue", "amenity": "bar", "name": "Ham Tree Inn", "phone": "+1-773-792-2072"}}, {"type": "node", "id": 4263932172, "lat": 41.9782705, "lon": -87.7705081, "tags": {"addr:city": "Chicago", "addr:housenumber": "5368", "addr:postcode": "60630", "addr:state": "IL", "addr:street": "North Milwaukee Avenue", "name": "Gladstone Park Laundromat", "shop": "laundry"}}, {"type": "node", "id": 4263932173, "lat": 41.9783028, "lon": -87.7705395, "tags": {"addr:city": "Chicago", "addr:housenumber": "5368", "addr:postcode": "60630", "addr:state": "IL", "addr:street": "North Milwaukee Avenue", "amenity": "bar", "name": "Zachary's"}}, {"type": "node", "id": 4263932178, "lat": 41.9808961, "lon": -87.7729393, "tags": {"amenity": "atm", "brand": "Bank of America", "brand:wikidata": "Q487907", "cash_in": "yes", "drive_through": "yes", "name": "Bank of America", "operator": "Bank of America", "operator:wikidata": "Q487907", "operator:wikipedia": "en:Bank of America"}}, {"type": "node", "id": 4265453763, "lat": 41.9824872, "lon": -87.7745756, "tags": {"addr:city": "Chicago", "addr:housenumber": "5540", "addr:postcode": "60630", "addr:state": "IL", "addr:street": "North Milwaukee Avenue", "amenity": "restaurant", "cuisine": "mexican", "name": "Tuxpan Mexican Grill"}}, {"type": "node", "id": 4517784417, "lat": 41.9685446, "lon": -87.7874703, "tags": {"addr:city": "Chicago", "addr:housenumber": "6346", "addr:postcode": "60630", "addr:state": "IL", "addr:street": "West Gunnison Street", "name": "Gaelic Imports", "shop": "convenience"}}, {"type": "node", "id": 4557558098, "lat": 41.992663, "lon": -87.7659092}, {"type": "node", "id": 4937751834, "lat": 41.9695905, "lon": -87.7620179, "tags": {"amenity": "bench", "backrest": "yes"}}, {"type": "node", "id": 4937751835, "lat": 41.9695574, "lon": -87.7619938, "tags": {"amenity": "bench", "backrest": "yes"}}, {"type": "node", "id": 4937751836, "lat": 41.9698506, "lon": -87.762042, "tags": {"amenity": "bench", "backrest": "no"}}, {"type": "node", "id": 4937751837, "lat": 41.9697791, "lon": -87.7620119, "tags": {"amenity": "bench", "backrest": "no"}}, {"type": "node", "id": 4937751843, "lat": 41.969871, "lon": -87.7622563, "tags": {"amenity": "bench", "backrest": "yes"}}, {"type": "node", "id": 5210965607, "lat": 41.9852061, "lon": -87.7680718, "tags": {"addr:city": "Chicago", "addr:housenumber": "5707", "addr:postcode": "60646", "addr:state": "IL", "addr:street": "North Central Avenue", "amenity": "restaurant", "cuisine": "italian;pizza;american;steak_house;ribs", "name": "Colletti's", "opening_hours": "Mo-Th 11:00-23:00"}}, {"type": "node", "id": 5210965609, "lat": 41.9897836, "lon": -87.7771781, "tags": {"addr:city": "Chicago", "addr:housenumber": "5961", "addr:postcode": "60646", "addr:state": "IL", "addr:street": "North Elston Avenue", "amenity": "restaurant", "cuisine": "polish", "name": "Smak Tak", "opening_hours": "11:00-21:00", "phone": "+1-773-763-1123", "takeaway": "yes"}}, {"type": "node", "id": 5623406086, "lat": 41.9692208, "lon": -87.7609158, "tags": {"addr:city": "Chicago", "addr:housenumber": "4855", "addr:postcode": "60630", "addr:state": "IL", "addr:street": "North Milwaukee Avenue", "amenity": "restaurant", "cuisine": "chinese", "delivery": "yes", "name": "Excelsior Garden", "outdoor_seating": "no", "takeaway": "yes"}}, {"type": "node", "id": 5648172638, "lat": 41.9679808, "lon": -87.760951, "tags": {"amenity": "bench", "backrest": "yes"}}, {"type": "node", "id": 6265057877, "lat": 41.9856444, "lon": -87.7771507, "tags": {"addr:city": "Chicago", "addr:housenumber": "5740", "addr:postcode": "60646", "addr:state": "IL", "addr:street": "North Milwaukee Avenue", "name": "Baking For The Takin", "phone": "+1-773-951-5025", "shop": "bakery"}}, {"type": "node", "id": 6282526106, "lat": 41.9823166, "lon": -87.7806658, "tags": {"addr:city": "Chicago", "addr:housenumber": "5569", "addr:postcode": "60630", "addr:state": "IL", "addr:street": "North Northwest Highway", "name": "Chicago Sweet Connection", "phone": "+1-773-283-4430", "shop": "bakery", "website": "https://www.sweetconnectionbakery.com/"}}, {"type": "node", "id": 6283857782, "lat": 41.9815209, "lon": -87.7623018, "tags": {"addr:city": "Chicago", "addr:housenumber": "5522", "addr:postcode": "60630", "addr:state": "IL", "addr:street": "North Elston Avenue", "amenity": "bar", "name": "Corrib Irish Pub", "phone": "+1-773-969-0692"}}, {"type": "node", "id": 6286963299, "lat": 41.9890852, "lon": -87.776465, "tags": {"addr:city": "Chicago", "addr:housenumber": "5930", "addr:postcode": "60646", "addr:state": "IL", "addr:street": "North Elston Avenue", "name": "European Classic Bakery", "phone": "+1-773-774-8755", "shop": "bakery"}}, {"type": "node", "id": 6303036499, "lat": 41.9805071, "lon": -87.7725366, "tags": {"addr:city": "Chicago", "addr:housenumber": "5450", "addr:postcode": "60630", "addr:state": "IL", "addr:street": "North Milwaukee Avenue", "name": "Sweet World Pastry", "phone": "+1-773-792-5566", "shop": "bakery"}}, {"type": "node", "id": 6317078369, "lat": 41.9838078, "lon": -87.7663036, "tags": {"addr:city": "Chicago", "addr:housenumber": "5640", "addr:postcode": "60630", "addr:state": "IL", "addr:street": "North Elston Avenue", "amenity": "cafe", "name": "Yellow Rose Cafe", "outdoor_seating": "yes", "phone": "+1-773-631-2297"}}, {"type": "node", "id": 6321708060, "lat": 41.9705803, "lon": -87.7628638, "tags": {"addr:city": "Chicago", "addr:housenumber": "4933", "addr:postcode": "60630", "addr:state": "IL", "addr:street": "North Milwaukee Avenue", "amenity": "bar", "name": "Rex Tavern", "phone": "+1-773-202-9444", "website": "https://www.rextavernchicago.com/"}}, {"type": "node", "id": 6325936220, "lat": 41.9805375, "lon": -87.7776143, "tags": {"addr:city": "Chicago", "addr:housenumber": "5485", "addr:postcode": "60630", "addr:state": "IL", "addr:street": "North Northwest Highway", "amenity": "bar", "name": "Vaughan\u2019s Pub - NW Side", "phone": "+1-773-631-9206", "website": "https://vaughanhospitality.com/"}}, {"type": "node", "id": 6340821364, "lat": 41.9943388, "lon": -87.7692028}, {"type": "node", "id": 6340821367, "lat": 41.9944822, "lon": -87.7706028}, {"type": "node", "id": 6340821368, "lat": 41.9940489, "lon": -87.7683541}, {"type": "node", "id": 6340821369, "lat": 41.9973369, "lon": -87.7802388}, {"type": "node", "id": 6340821371, "lat": 41.9973265, "lon": -87.7828953}, {"type": "node", "id": 6340821380, "lat": 41.993995, "lon": -87.7682643}, {"type": "node", "id": 6340821381, "lat": 41.9942719, "lon": -87.7688724}, {"type": "node", "id": 6340821384, "lat": 41.9934869, "lon": -87.7676621}, {"type": "node", "id": 6340822586, "lat": 41.9906657, "lon": -87.7661478}, {"type": "node", "id": 6340822594, "lat": 41.9944052, "lon": -87.7702796}, {"type": "node", "id": 6340822597, "lat": 41.9941496, "lon": -87.7685537}, {"type": "node", "id": 6340822613, "lat": 41.992043, "lon": -87.7658298}, {"type": "node", "id": 6340822614, "lat": 41.9932499, "lon": -87.7671469}, {"type": "node", "id": 6340822616, "lat": 41.9938504, "lon": -87.7681025}, {"type": "node", "id": 6340822635, "lat": 41.9962921, "lon": -87.7828734}, {"type": "node", "id": 6340822636, "lat": 41.9922442, "lon": -87.7742425}, {"type": "node", "id": 6340822642, "lat": 41.9924578, "lon": -87.7733523}, {"type": "node", "id": 6340822664, "lat": 41.9943855, "lon": -87.7700255}, {"type": "node", "id": 6340822670, "lat": 41.9944391, "lon": -87.7704442}, {"type": "node", "id": 6340822707, "lat": 41.9945673, "lon": -87.7707736}, {"type": "node", "id": 6340822726, "lat": 41.9936335, "lon": -87.7679376}, {"type": "node", "id": 6340837862, "lat": 41.9910163, "lon": -87.7707788}, {"type": "node", "id": 6344533255, "lat": 41.9970633, "lon": -87.7769095}, {"type": "node", "id": 6344533256, "lat": 41.997149, "lon": -87.7768424}, {"type": "node", "id": 6344533258, "lat": 41.9971538, "lon": -87.7767491}, {"type": "node", "id": 6344533268, "lat": 41.997072, "lon": -87.7765802}, {"type": "node", "id": 6344533272, "lat": 41.9968707, "lon": -87.7763496}, {"type": "node", "id": 6344533278, "lat": 41.9924125, "lon": -87.7656913}, {"type": "node", "id": 6344533280, "lat": 41.9967072, "lon": -87.7761511}, {"type": "node", "id": 6344533284, "lat": 41.9965856, "lon": -87.7758641}, {"type": "node", "id": 6344533496, "lat": 41.9965737, "lon": -87.77562}, {"type": "node", "id": 6344533501, "lat": 41.9966586, "lon": -87.7751446}, {"type": "node", "id": 6344533504, "lat": 41.9925046, "lon": -87.7656617}, {"type": "node", "id": 6344533507, "lat": 41.9968966, "lon": -87.7744023}, {"type": "node", "id": 6344533539, "lat": 41.99509, "lon": -87.7803103}, {"type": "node", "id": 6344533577, "lat": 41.996525, "lon": -87.7717623}, {"type": "node", "id": 6344533581, "lat": 41.9966985, "lon": -87.7721432}, {"type": "node", "id": 6344533606, "lat": 41.9925752, "lon": -87.7657319}, {"type": "node", "id": 6344533643, "lat": 41.9943179, "lon": -87.7690557}, {"type": "node", "id": 6344533650, "lat": 41.9949184, "lon": -87.7714727}, {"type": "node", "id": 6344533651, "lat": 41.9955782, "lon": -87.7712473}, {"type": "node", "id": 6344533657, "lat": 41.9951018, "lon": -87.7713573}, {"type": "node", "id": 6344533760, "lat": 41.9968388, "lon": -87.7799436}, {"type": "node", "id": 6344533765, "lat": 41.9959749, "lon": -87.771301}, {"type": "node", "id": 6344533778, "lat": 41.9969369, "lon": -87.7800678}, {"type": "node", "id": 6344533886, "lat": 41.9963058, "lon": -87.77147}, {"type": "node", "id": 6344533958, "lat": 41.9908857, "lon": -87.7661104}, {"type": "node", "id": 6344533976, "lat": 41.9966526, "lon": -87.7796105}, {"type": "node", "id": 6344534112, "lat": 41.9970142, "lon": -87.7779373}, {"type": "node", "id": 6344534115, "lat": 41.9970672, "lon": -87.7781862}, {"type": "node", "id": 6344534123, "lat": 41.9968846, "lon": -87.7776369}, {"type": "node", "id": 6344534124, "lat": 41.9968727, "lon": -87.7773606}, {"type": "node", "id": 6344534129, "lat": 41.9969237, "lon": -87.7770758}, {"type": "node", "id": 6344534139, "lat": 41.9969544, "lon": -87.7741368}, {"type": "node", "id": 6344534147, "lat": 41.9968368, "lon": -87.7726454}, {"type": "node", "id": 6344534155, "lat": 41.9969504, "lon": -87.7735333}, {"type": "node", "id": 6344534330, "lat": 41.9970102, "lon": -87.7783665}, {"type": "node", "id": 6344534337, "lat": 41.9968719, "lon": -87.778543}, {"type": "node", "id": 6344534338, "lat": 41.9955124, "lon": -87.7812108}, {"type": "node", "id": 6344534353, "lat": 41.9966893, "lon": -87.7788439}, {"type": "node", "id": 6344534359, "lat": 41.9966295, "lon": -87.7792865}, {"type": "node", "id": 6369465146, "lat": 41.9825588, "lon": -87.783751}, {"type": "node", "id": 6369465147, "lat": 41.9825194, "lon": -87.7836944}, {"type": "node", "id": 6369465148, "lat": 41.9824707, "lon": -87.7836732}, {"type": "node", "id": 6369465149, "lat": 41.9824326, "lon": -87.7836927}, {"type": "node", "id": 6369465150, "lat": 41.9824339, "lon": -87.7837422}, {"type": "node", "id": 6369465151, "lat": 41.9824681, "lon": -87.7838378}, {"type": "node", "id": 6369465152, "lat": 41.9817399, "lon": -87.7833573}, {"type": "node", "id": 6369465153, "lat": 41.9817872, "lon": -87.7834192}, {"type": "node", "id": 6369465154, "lat": 41.9817978, "lon": -87.7834953}, {"type": "node", "id": 6369465155, "lat": 41.9817728, "lon": -87.7835166}, {"type": "node", "id": 6369465156, "lat": 41.9817162, "lon": -87.7834865}, {"type": "node", "id": 6369465157, "lat": 41.9815649, "lon": -87.783191}, {"type": "node", "id": 6369465158, "lat": 41.9815873, "lon": -87.7831467}, {"type": "node", "id": 6369465159, "lat": 41.9816412, "lon": -87.7831467}, {"type": "node", "id": 6369465160, "lat": 41.9816767, "lon": -87.7831892}, {"type": "node", "id": 6369465161, "lat": 41.9817044, "lon": -87.7832954}, {"type": "node", "id": 6369465186, "lat": 41.9784512, "lon": -87.7774115}, {"type": "node", "id": 6369465187, "lat": 41.9784525, "lon": -87.777461}, {"type": "node", "id": 6369465188, "lat": 41.9783999, "lon": -87.7774787}, {"type": "node", "id": 6369465189, "lat": 41.9783354, "lon": -87.7774645}, {"type": "node", "id": 6369465190, "lat": 41.978271, "lon": -87.7774062}, {"type": "node", "id": 6369465191, "lat": 41.978242, "lon": -87.7773548}, {"type": "node", "id": 6369465192, "lat": 41.9782275, "lon": -87.777277}, {"type": "node", "id": 6369465193, "lat": 41.9782512, "lon": -87.7771938}, {"type": "node", "id": 6369465194, "lat": 41.9782789, "lon": -87.7771637}, {"type": "node", "id": 6369465195, "lat": 41.9783052, "lon": -87.7771814}, {"type": "node", "id": 6369465196, "lat": 41.9783236, "lon": -87.777231}, {"type": "node", "id": 6369465197, "lat": 41.9783354, "lon": -87.7772894}, {"type": "node", "id": 6369465198, "lat": 41.9783709, "lon": -87.7773478}, {"type": "node", "id": 6369465199, "lat": 41.9784091, "lon": -87.7773672}, {"type": "node", "id": 6369465200, "lat": 41.9784315, "lon": -87.7773831}, {"type": "node", "id": 6412876025, "lat": 41.9695823, "lon": -87.7624194}, {"type": "node", "id": 6412876026, "lat": 41.9694429, "lon": -87.7626862}, {"type": "node", "id": 6412876027, "lat": 41.9694425, "lon": -87.7627287}, {"type": "node", "id": 6558670534, "lat": 41.990413, "lon": -87.7662217}, {"type": "node", "id": 6558670539, "lat": 41.9951668, "lon": -87.780474}, {"type": "node", "id": 6558670542, "lat": 41.9973372, "lon": -87.7802142}, {"type": "node", "id": 7510010482, "lat": 41.9793785, "lon": -87.75723}, {"type": "node", "id": 7510010483, "lat": 41.979341, "lon": -87.7571689}, {"type": "node", "id": 7944082443, "lat": 41.9774808, "lon": -87.7687052, "tags": {"addr:city": "Chicago", "addr:housenumber": "5303", "addr:postcode": "60630", "addr:state": "IL", "addr:street": "North Milwaukee Avenue", "amenity": "restaurant", "name": "Paterno's Pizza", "website": "https://www.paternopizza.com/"}}, {"type": "node", "id": 10212297723, "lat": 41.990412, "lon": -87.7662057}, {"type": "node", "id": 10810668909, "lat": 41.9750024, "lon": -87.7688943, "tags": {"addr:city": "Chicago", "addr:housenumber": "5210", "addr:postcode": "60630", "addr:state": "IL", "addr:street": "North Northwest Highway", "brand": "BP Shop", "brand:wikidata": "Q152057", "name": "BP Shop", "shop": "convenience"}}, {"type": "node", "id": 10876815006, "lat": 41.990411, "lon": -87.7661902}, {"type": "node", "id": 10879729819, "lat": 41.9942147, "lon": -87.7687067}, {"type": "node", "id": 10879729820, "lat": 41.9939286, "lon": -87.7681775}, {"type": "node", "id": 10879729821, "lat": 41.9935852, "lon": -87.767879}, {"type": "node", "id": 10879729822, "lat": 41.992541, "lon": -87.7656833}, {"type": "node", "id": 10885448476, "lat": 41.9898764, "lon": -87.7673123}, {"type": "node", "id": 10885448483, "lat": 41.9899686, "lon": -87.7672354}, {"type": "node", "id": 10885448484, "lat": 41.9900442, "lon": -87.7670829}, {"type": "node", "id": 10885448485, "lat": 41.9901016, "lon": -87.7669283}, {"type": "node", "id": 10885448486, "lat": 41.990147, "lon": -87.7666638}, {"type": "node", "id": 10885448487, "lat": 41.9901818, "lon": -87.7664889}, {"type": "node", "id": 10885448488, "lat": 41.9902589, "lon": -87.766316}, {"type": "node", "id": 10885448534, "lat": 41.9911312, "lon": -87.7707442}, {"type": "node", "id": 10885448535, "lat": 41.9912703, "lon": -87.7707218}, {"type": "node", "id": 10885448536, "lat": 41.9913927, "lon": -87.7707544}, {"type": "node", "id": 10885448537, "lat": 41.9914819, "lon": -87.7708276}, {"type": "node", "id": 10885448538, "lat": 41.9915469, "lon": -87.7709293}, {"type": "node", "id": 10885448539, "lat": 41.9915817, "lon": -87.7710615}, {"type": "node", "id": 10885448540, "lat": 41.991624, "lon": -87.7715029}, {"type": "node", "id": 10885448541, "lat": 41.9916588, "lon": -87.7721253}, {"type": "node", "id": 10885448542, "lat": 41.9917208, "lon": -87.7725179}, {"type": "node", "id": 10885448543, "lat": 41.9917873, "lon": -87.7727274}, {"type": "node", "id": 10885448544, "lat": 41.9918901, "lon": -87.772882}, {"type": "node", "id": 10885448545, "lat": 41.9920579, "lon": -87.7730671}, {"type": "node", "id": 10885448546, "lat": 41.992324, "lon": -87.7732624}, {"type": "node", "id": 10900075325, "lat": 41.9914483, "lon": -87.7660157}, {"type": "node", "id": 10900075328, "lat": 41.9916172, "lon": -87.7659744}, {"type": "node", "id": 10900075396, "lat": 41.986818, "lon": -87.7622399, "tags": {"amenity": "bench"}}, {"type": "node", "id": 11826579074, "lat": 41.9695788, "lon": -87.7624261}, {"type": "node", "id": 11826579075, "lat": 41.969497, "lon": -87.7625826}, {"type": "way", "id": 26195853, "nodes": [286841222, 2168616082, 286841223, 2168616095, 2168616159, 2168616093, 2168616115, 2168616099, 2168616067, 286841225, 2168616125, 2168616075, 286841226, 2168616069, 2168616072, 2168616169, 286841222], "tags": {"ele": "189", "gnis:county_id": "031", "gnis:created": "09/09/1997", "gnis:feature_id": "1764299", "gnis:state_id": "17", "leisure": "park", "name": "Austin-Foster Park", "operator": "Chicago Park District", "operator:type": "public", "operator:wikidata": "Q2963322", "operator:wikipedia": "en:Chicago Park District", "wikidata": "Q49539246"}}, {"type": "way", "id": 27861467, "nodes": [305904970, 305904971, 2144878422, 2144878534, 2144878427, 305904972, 2144878420, 2144878273, 2144878523, 305904973, 2144878499, 2144878387, 2144878441, 2144878413, 2144878359, 2144878563, 305904970], "tags": {"gnis:feature_id": "416760", "leisure": "park", "name": "Roberts Square Park", "operator": "Chicago Park District", "operator:type": "public", "operator:wikidata": "Q2963322", "operator:wikipedia": "en:Chicago Park District", "wikidata": "Q49552173"}}, {"type": "way", "id": 27861474, "nodes": [305905014, 305905015, 305905016, 305905017, 305905018, 305905019, 305905014], "tags": {"addr:city": "Chicago", "addr:housenumber": "5025", "addr:postcode": "60630", "addr:state": "IL", "addr:street": "North Laramie Avenue", "amenity": "school", "name": "Beaubien Elementary School", "operator": "Chicago Public Schools", "operator:short": "CPS", "operator:type": "public", "operator:wikidata": "Q2963340", "operator:wikipedia": "en:Chicago Public Schools"}}, {"type": "way", "id": 27861523, "nodes": [305905635, 305905636, 305905637, 305905638, 305905635], "tags": {"addr:city": "Chicago", "addr:housenumber": "5414", "addr:postcode": "60630", "addr:state": "IL", "addr:street": "North Linder Avenue", "amenity": "school", "ele": "187", "gnis:county_id": "031", "gnis:created": "09/30/1999", "gnis:feature_id": "408292", "gnis:state_id": "17", "name": "James B. Farnsworth Elementary School", "operator": "Chicago Public Schools", "operator:short": "CPS", "operator:type": "public", "operator:wikidata": "Q2963340", "operator:wikipedia": "en:Chicago Public Schools"}}, {"type": "way", "id": 27861631, "nodes": [305906790, 305906791, 305906792, 2144916905, 2144916942, 2144916946, 2144916964, 305906793, 2144878408, 2144878296, 2144878373, 305906794, 305906790], "tags": {"addr:city": "Chicago", "addr:housenumber": "4822", "addr:postcode": "60630", "addr:state": "IL", "addr:street": "North Long Avenue", "leisure": "park", "name": "Jefferson Memorial Park", "operator": "Chicago Park District", "operator:type": "public", "operator:wikidata": "Q2963322", "operator:wikipedia": "en:Chicago Park District", "website": "https://www.chicagoparkdistrict.com/parks/Jefferson-Memorial-Park/", "wikidata": "Q3176658", "wikipedia": "en:Jefferson Park (Chicago park)"}}, {"type": "way", "id": 162704482, "nodes": [1745518263, 1745518690, 1745518390, 1745518238, 1745518192, 1745518263], "tags": {"addr:city": "Chicago", "addr:housenumber": "4801", "addr:postcode": "60630", "addr:state": "IL", "addr:street": "North Milwaukee Avenue", "addr:street:name": "Milwaukee", "addr:street:prefix": "North", "addr:street:type": "Avenue", "amenity": "cafe", "brand": "Costa", "brand:wikidata": "Q608845", "building": "retail", "building:levels": "1", "chicago:building_id": "844615", "cuisine": "coffee_shop", "name": "Costa", "takeaway": "yes"}}, {"type": "way", "id": 162705754, "nodes": [1745526416, 1745526356, 1745526891, 1745527428, 1745527366, 1745528296, 1745527899, 1745527281, 1745527030, 1745526774, 1745526416], "tags": {"addr:city": "Chicago", "addr:housenumber": "4874", "addr:postcode": "60630", "addr:state": "IL", "addr:street": "North Milwaukee Avenue", "addr:street:name": "Milwaukee", "addr:street:prefix": "North", "addr:street:type": "Avenue", "amenity": "bar", "building": "commercial", "building:levels": "2", "chicago:building_id": "101987", "name": "Jefferson Inn", "phone": "+1-773-283-5522", "smoking": "isolated"}}, {"type": "way", "id": 162809709, "nodes": [1746214377, 1746214750, 1746214513, 1746215787, 1746216238, 1746214955, 1746214924, 1746214695, 1746214377], "tags": {"addr:city": "Chicago", "addr:housenumber": "5151", "addr:postcode": "60630", "addr:state": "IL", "addr:street": "North Milwaukee Avenue", "addr:street:name": "Milwaukee", "addr:street:prefix": "North", "addr:street:type": "Avenue", "alt_name": "Jefferson Park District Police Station", "amenity": "police", "branch": "Jefferson Park", "building": "public", "building:levels": "2", "chicago:building_id": "815656", "name": "Chicago Police Department 16th District", "opening_hours": "24/7", "operator": "Chicago Police Department", "operator:wikidata": "Q1340186", "operator:wikipedia": "en:Chicago Police Department"}}, {"type": "way", "id": 163177651, "nodes": [1749353623, 1749353843, 1749353851, 1749353634, 4186624671, 4186624668, 1749353623], "tags": {"addr:city": "Chicago", "addr:housenumber": "4835", "addr:postcode": "60630", "addr:state": "IL", "addr:street": "North Austin Avenue", "addr:street:name": "Austin", "addr:street:prefix": "North", "addr:street:type": "Avenue", "amenity": "restaurant", "building": "yes", "building:levels": "1", "chicago:building_id": "105366", "cuisine": "barbecue", "name": "Earl's BBQ", "not:brand:wikidata": "Q5326525"}}, {"type": "way", "id": 163179442, "nodes": [1749363459, 1749363541, 1749364352, 1749364287, 1749363459], "tags": {"addr:city": "Chicago", "addr:housenumber": "5722", "addr:postcode": "60630", "addr:state": "IL", "addr:street": "West Higgins Avenue", "addr:street:name": "Higgins", "addr:street:prefix": "West", "addr:street:type": "Avenue", "amenity": "bar", "building": "yes", "building:levels": "2", "chicago:building_id": "93968", "name": "Bar 57 West", "phone": "+1-773-427-6635"}}, {"type": "way", "id": 163179995, "nodes": [1749366851, 1749366891, 1749368051, 1749367996, 1749367938, 1749367857, 1749367796, 1749367685, 1749367645, 1749366851], "tags": {"addr:city": "Chicago", "addr:housenumber": "5862", "addr:postcode": "60630", "addr:state": "IL", "addr:street": "West Higgins Avenue", "addr:street:name": "Higgins", "addr:street:prefix": "West", "addr:street:type": "Avenue", "building": "yes", "building:levels": "2", "chicago:building_id": "89471", "name": "Wall's Flower Shop", "shop": "florist"}}, {"type": "way", "id": 163180297, "nodes": [1749367098, 1749367176, 1749367225, 1749367306, 1749367414, 1749367312, 1749367426, 1749367393, 1749366893, 1749367098], "tags": {"addr:city": "Chicago", "addr:housenumber": "5961", "addr:postcode": "60630", "addr:state": "IL", "addr:street": "West Higgins Avenue", "addr:street:name": "Higgins", "addr:street:prefix": "West", "addr:street:type": "Avenue", "brand": "Mobil Mart", "brand:wikidata": "Q109676002", "building": "yes", "chicago:building_id": "843727", "name": "Mobil Mart", "shop": "convenience"}}, {"type": "way", "id": 163180298, "nodes": [1749353274, 1749353275, 1749353287, 1749353285, 1749353804, 1749353813, 1749353818, 1749353274], "tags": {"addr:city": "Chicago", "addr:housenumber": "6000", "addr:postcode": "60630", "addr:state": "IL", "addr:street": "West Gunnison Street", "addr:street:name": "Gunnison", "addr:street:prefix": "West", "addr:street:type": "Street", "amenity": "bar", "building": "yes", "chicago:building_id": "105421", "name": "Charlotte's Bar & Grill"}}, {"type": "way", "id": 163180301, "nodes": [1749370372, 1749370620, 1749370754, 1749370787, 1749371059, 1749371105, 1749371325, 1749371286, 1749371333, 1749371111, 1749370395, 1749370435, 1749370372], "tags": {"addr:city": "Chicago", "addr:housenumber": "6000", "addr:postcode": "60630", "addr:state": "IL", "addr:street": "West Higgins Avenue", "addr:street:name": "Higgins", "addr:street:prefix": "West", "addr:street:type": "Avenue", "brand": "7-Eleven", "brand:wikidata": "Q259340", "building": "retail", "building:levels": "1", "chicago:building_id": "86333", "contact:website": "https://www.7-eleven.com/locations/il/chicago/6000-w-higgins-ave-30105", "name": "7-Eleven", "shop": "convenience"}}, {"type": "way", "id": 163220548, "nodes": [1749664210, 1749665672, 1749666612, 1749665651, 1749664210], "tags": {"addr:city": "Chicago", "addr:housenumber": "5250", "addr:postcode": "60630", "addr:state": "IL", "addr:street": "North Northwest Highway", "addr:street:name": "Northwest", "addr:street:prefix": "North", "addr:street:type": "Highway", "building": "commercial", "building:levels": "1", "chicago:building_id": "77133", "leisure": "bowling_alley", "name": "Habetler Bowl", "sport": "10pin", "website": "https://habetlerbowl.com/"}}, {"type": "way", "id": 163220727, "nodes": [1749666420, 1749666768, 1749667082, 1749666667, 1749666420], "tags": {"addr:city": "Chicago", "addr:housenumber": "5310", "addr:postcode": "60630", "addr:state": "IL", "addr:street": "North Milwaukee Avenue", "addr:street:name": "Milwaukee", "addr:street:prefix": "North", "addr:street:type": "Avenue", "amenity": "restaurant", "building": "retail", "building:levels": "1", "chicago:building_id": "76488", "cuisine": "pancake", "name": "Elly's Pancake House"}}, {"type": "way", "id": 163221156, "nodes": [1749669291, 1749669564, 1749669861, 1749670020, 1749669859, 1749669797, 1749669291], "tags": {"addr:city": "Chicago", "addr:housenumber": "5346", "addr:postcode": "60630", "addr:state": "IL", "addr:street": "North Milwaukee Avenue", "addr:street:name": "Milwaukee", "addr:street:prefix": "North", "addr:street:type": "Avenue", "amenity": "restaurant", "building": "yes", "building:levels": "1", "chicago:building_id": "73273", "cuisine": "chinese", "name": "Moy Lee Chinese Restaurant"}}, {"type": "way", "id": 163226336, "nodes": [1749665929, 1749666090, 1749666433, 1749666254, 1749665929], "tags": {"addr:housenumber": "6348", "addr:street": "West Higgins Avenue", "addr:street:name": "Higgins", "addr:street:prefix": "West", "addr:street:type": "Avenue", "amenity": "restaurant", "building": "yes", "chicago:building_id": "77684", "cuisine": "coffee_shop", "name": "The Big Top Restaurant"}}, {"type": "way", "id": 194838776, "nodes": [354106589, 2053512399, 2053512491, 2053512468, 2053512411, 2053512391, 2053512466, 2053512415, 2053512464, 2053512409, 2053512397, 2053512420, 354106589], "tags": {"addr:city": "Chicago", "addr:housenumber": "5421", "addr:postcode": "60630", "addr:state": "IL", "addr:street": "North Menard Avenue", "ele": "189", "gnis:county_id": "031", "gnis:created": "01/15/1980", "gnis:feature_id": "409048", "gnis:state_id": "17", "leisure": "park", "name": "Gladstone Park", "operator": "Chicago Park District", "operator:type": "public", "operator:wikidata": "Q2963322", "operator:wikipedia": "en:Chicago Park District", "wikidata": "Q34881805"}}, {"type": "way", "id": 194859516, "nodes": [2053834260, 2053834273, 2053834261, 2053834244, 2053834266, 2053834272, 2053834260], "tags": {"amenity": "school", "denomination": "roman_catholic", "ele": "187", "gnis:county_id": "031", "gnis:created": "01/15/1980", "gnis:feature_id": "417247", "gnis:state_id": "17", "name": "Saint Cornelius School", "operator": "Archdiocese of Chicago", "operator:type": "religious", "operator:wikidata": "Q1364344", "religion": "christian"}}, {"type": "way", "id": 206920692, "nodes": [354214183, 2169870976, 2144919918, 2144919891, 2144919888, 2144919914, 354214183], "tags": {"amenity": "school", "denomination": "roman_catholic", "ele": "189", "gnis:county_id": "031", "gnis:created": "09/09/1997", "gnis:feature_id": "1764338", "gnis:state_id": "17", "name": "Saint Constance School", "operator": "Archdiocese of Chicago", "operator:type": "religious", "operator:wikidata": "Q1364344", "religion": "christian"}}, {"type": "way", "id": 279659232, "nodes": [2838650361, 2838650362, 2838650363, 2838650364, 2838650361], "tags": {"leisure": "park"}}, {"type": "way", "id": 329025641, "nodes": [3358447985, 3358447986, 3358447987, 7510010483, 7510010482, 3358447988, 3358447989, 3358447990, 3358447985], "tags": {"addr:city": "Chicago", "addr:housenumber": "5353", "addr:postcode": "60630", "addr:state": "IL", "addr:street": "North Elston Avenue", "addr:street:name": "Elston", "addr:street:prefix": "North", "addr:street:type": "Avenue", "branch": "Jefferson Park", "brand": "Mariano's Fresh Market", "brand:wikidata": "Q55622168", "building": "retail", "building:levels": "1", "chicago:building_id": "66434", "name": "Mariano's Fresh Market", "opening_hours": "06:00-22:00", "shop": "supermarket", "short_name": "Mariano's", "website": "https://www.marianos.com/stores/details/531/00507"}}, {"type": "way", "id": 416495647, "nodes": [4172392093, 4172392094, 4172392095, 4172392096, 4172392097, 4172392098, 4172392093], "tags": {"addr:city": "Chicago", "addr:housenumber": "4914", "addr:postcode": "60630", "addr:state": "IL", "addr:street": "North Milwaukee Avenue", "amenity": "restaurant", "building": "yes", "chicago:building_id": "100756", "cuisine": "american", "name": "Gale Street Inn", "phone": "+1-773-725-1300", "website": "http://www.galestreet.com/"}}, {"type": "way", "id": 418199446, "nodes": [4186479475, 4186479471, 4186479476, 4186479477, 4186479475], "tags": {"addr:city": "Chicago", "addr:housenumber": "4808", "addr:postcode": "60630", "addr:state": "IL", "addr:street": "North Milwaukee Avenue", "amenity": "restaurant", "building": "yes", "cuisine": "mexican", "name": "Taqueria La Estrella"}}, {"type": "way", "id": 677184314, "nodes": [6340822642, 6340822636, 6344533539, 6558670539, 6344534338, 6340822635, 6340821371, 6340821369, 6558670542, 2078125275, 2078125643, 6344533778, 6344533760, 6344533976, 6344534359]}, {"type": "way", "id": 680259903, "nodes": [6369465146, 6369465147, 6369465148, 6369465149, 6369465150, 6369465151, 6369465146], "tags": {"leisure": "garden", "name": "KE18", "operator": "Chicago Gateway Green"}}, {"type": "way", "id": 680259904, "nodes": [6369465152, 6369465153, 6369465154, 6369465155, 6369465156, 6369465157, 6369465158, 6369465159, 6369465160, 6369465161, 6369465152], "tags": {"leisure": "garden", "name": "KE21", "operator": "Chicago Gateway Green"}}, {"type": "way", "id": 680259906, "nodes": [6369465186, 6369465187, 6369465188, 6369465189, 6369465190, 6369465191, 6369465192, 6369465193, 6369465194, 6369465195, 6369465196, 6369465197, 6369465198, 6369465199, 6369465200, 6369465186], "tags": {"leisure": "garden", "name": "KE39-Hyatt Regency", "operator": "Chicago Gateway Green"}}, {"type": "way", "id": 684481665, "nodes": [1745527899, 6412876025, 11826579074, 11826579075, 6412876026, 6412876027, 1745526356, 1745526416, 1745526774, 1745527030, 1745527281, 1745527899], "tags": {"addr:city": "Chicago", "addr:housenumber": "4872", "addr:postcode": "60630", "addr:state": "IL", "addr:street": "North Milwaukee Avenue", "amenity": "cafe", "building": "commercial", "internet_access": "wlan", "name": "Weston's Coffee & Tap Co.", "opening_hours": "Mo-Th 6:30-19:00; Fr 6:30-20:30; Sa 7:30-20:30; Su 7:30-19:00", "outdoor_seating": "no", "phone": "+1-708-669-7625", "website": "https://www.westonscoffee.com/"}}, {"type": "way", "id": 1171447685, "nodes": [6344534359, 6344534353, 6344534337, 6344534330, 6344534115, 6344534112, 6344534123, 6344534124, 6344534129, 6344533255, 6344533256, 6344533258, 6344533268, 6344533272, 6344533280, 6344533284, 6344533496, 6344533501, 6344533507, 6344534139, 6344534155, 6344534147, 6344533581, 6344533577, 6344533886, 6344533765, 6344533651, 6344533657, 6344533650, 6340822707, 6340821367, 6340822670, 6340822594, 6340822664, 6340821364, 6344533643, 6340821381, 10879729819, 6340822597, 6340821368, 6340821380, 10879729820, 6340822616, 6340822726, 10879729821, 6340821384, 6340822614, 4557558098, 6344533606, 10879729822, 6344533504, 6344533278, 6340822613, 10900075328, 10900075325, 6344533958, 6340822586, 10876815006, 10212297723, 6558670534, 2078187694]}, {"type": "way", "id": 1171447688, "nodes": [2078187694, 10885448488, 10885448487, 10885448486, 10885448485, 10885448484, 10885448483, 10885448476, 6340837862]}, {"type": "way", "id": 1171447689, "nodes": [6340837862, 10885448534, 10885448535, 10885448536, 10885448537, 10885448538, 10885448539, 10885448540, 10885448541, 10885448542, 10885448543, 10885448544, 10885448545, 10885448546, 6340822642]}, {"type": "relation", "id": 15840067, "members": [{"type": "way", "ref": 1171447688, "role": "outer"}, {"type": "way", "ref": 1171447685, "role": "outer"}, {"type": "way", "ref": 677184314, "role": "outer"}, {"type": "way", "ref": 1171447689, "role": "outer"}], "tags": {"addr:city": "Chicago", "addr:housenumber": "6100", "addr:postcode": "60646", "addr:state": "IL", "addr:street": "North Central Avenue", "leisure": "golf_course", "name": "Edgebrook Golf Course", "operator": "Indigo Sports", "owner": "Forest Preserve District of Cook County", "ownership": "government", "type": "multipolygon", "website": "https://edgebrook.forestpreservegolf.com/"}}]}